zhmc_log_forwarder/__init__.py
zhmc_log_forwarder/_version_scm.py
zhmc_log_forwarder/version.py
zhmc_log_forwarder/zhmc_log_forwarder.py
zhmc_log_forwarder/zhmc_log_messages.yml
zhmc_log_forwarder-1.1.0.dist-info/licenses/AUTHORS.md
zhmc_log_forwarder-1.1.0.dist-info/licenses/LICENSE
zhmc_log_forwarder-1.1.0.dist-info/METADATA
zhmc_log_forwarder-1.1.0.dist-info/WHEEL
zhmc_log_forwarder-1.1.0.dist-info/entry_points.txt
zhmc_log_forwarder-1.1.0.dist-info/top_level.txt
zhmc_log_forwarder-1.1.0.dist-info/zip-safe
zhmc_log_forwarder-1.1.0.dist-info/RECORD
