Metadata-Version: 2.4
Name: zhmc_log_forwarder
Version: 1.1.0
Summary: A log forwarder for the IBM Z HMC
Author-email: Andreas Maier <maiera@de.ibm.com>
Maintainer-email: Andreas Maier <maiera@de.ibm.com>
License: Apache License, Version 2.0
Project-URL: Homepage, https://github.com/zhmcclient/zhmc-log-forwarder
Project-URL: Bug Tracker, https://github.com/zhmcclient/zhmc-log-forwarder/issues
Project-URL: Documentation, https://zhmc-log-forwarder.readthedocs.io/en/latest/
Project-URL: Source Code, https://github.com/zhmcclient/zhmc-log-forwarder
Project-URL: Changelog, https://zhmc-log-forwarder.readthedocs.io/en/latest/changes.html
Keywords: hmc,prometheus,monitoring
Platform: any
Classifier: License :: OSI Approved :: Apache Software License
Classifier: Development Status :: 5 - Production/Stable
Classifier: Intended Audience :: Information Technology
Classifier: Intended Audience :: System Administrators
Classifier: Topic :: System :: Systems Administration
Classifier: Environment :: Console
Classifier: Operating System :: OS Independent
Classifier: Programming Language :: Python :: 3
Classifier: Programming Language :: Python :: 3.8
Classifier: Programming Language :: Python :: 3.9
Classifier: Programming Language :: Python :: 3.10
Classifier: Programming Language :: Python :: 3.11
Classifier: Programming Language :: Python :: 3.12
Classifier: Programming Language :: Python :: 3.13
Requires-Python: >=3.8
License-File: LICENSE
License-File: AUTHORS.md
Requires-Dist: zhmcclient>=1.18.2
Requires-Dist: attrs>=22.2.0
Requires-Dist: PyYAML>=6.0.2
Requires-Dist: python-dateutil>=2.8.2
Requires-Dist: requests>=2.31.0
Requires-Dist: jsonschema>=4.18.0
Dynamic: license-file
